{"cameraMode":{"drawMode":0,"name":"Shaded","section":"Shading Mode"},"sceneLighting":true,"audioPlay":false,"sceneViewState":{"m_AlwaysRefresh":false,"showFog":true,"showSkybox":true,"showFlares":true,"showImageEffects":true,"showParticleSystems":true,"showVisualEffectGraphs":true,"m_FxEnabled":true},"in2DMode":false,"pivot":{"x":-4.392221450805664,"y":-5.376723289489746,"z":0.1754816174507141},"rotation":{"x":0.23767122626304627,"y":0.6637413501739502,"z":-0.23585164546966554,"w":0.668944239616394},"size":7.1263427734375,"orthographic":false}